recognizers_text/__init__.py
recognizers_text/culture.py
recognizers_text/extractor.py
recognizers_text/meta_data.py
recognizers_text/model.py
recognizers_text/parser.py
recognizers_text/recognizer.py
recognizers_text/utilities.py
recognizers_text/matcher/__init__.py
recognizers_text/matcher/aa_node.py
recognizers_text/matcher/abstract_matcher.py
recognizers_text/matcher/ac_automaton.py
recognizers_text/matcher/match_result.py
recognizers_text/matcher/match_strategy.py
recognizers_text/matcher/matcher.py
recognizers_text/matcher/node.py
recognizers_text/matcher/number_with_unit_tokenizer.py
recognizers_text/matcher/simple_tokenizer.py
recognizers_text/matcher/string_matcher.py
recognizers_text/matcher/token.py
recognizers_text/matcher/tokenizer.py
recognizers_text/matcher/trie_tree.py
recognizers_text-1.0.2a2.dist-info/METADATA
recognizers_text-1.0.2a2.dist-info/WHEEL
recognizers_text-1.0.2a2.dist-info/top_level.txt
recognizers_text-1.0.2a2.dist-info/RECORD
